{
 "A": [
  [
   "Mexico",
   1943,
   82
  ],
  [
   "South Korea",
   1877,
   77
  ],
  [
   "Czech Republic",
   1786,
   67
  ],
  [
   "South Africa",
   1652,
   46
  ]
 ],
 "B": [
  [
   "Switzerland",
   1955,
   94
  ],
  [
   "Canada",
   1899,
   86
  ],
  [
   "Bosnia and Herzegovina",
   1642,
   48
  ],
  [
   "Qatar",
   1561,
   39
  ]
 ],
 "C": [
  [
   "Brazil",
   2064,
   98
  ],
  [
   "Morocco",
   1984,
   91
  ],
  [
   "Scotland",
   1825,
   56
  ],
  [
   "Haiti",
   1716,
   16
  ]
 ],
 "D": [
  [
   "Turkey",
   1961,
   67
  ],
  [
   "Paraguay",
   1915,
   62
  ],
  [
   "Australia",
   1895,
   76
  ],
  [
   "United States",
   1819,
   68
  ]
 ],
 "E": [
  [
   "Ecuador",
   2020,
   90
  ],
  [
   "Germany",
   1991,
   97
  ],
  [
   "Ivory Coast",
   1790,
   79
  ],
  [
   "Curaçao",
   1601,
   9
  ]
 ],
 "F": [
  [
   "Netherlands",
   2002,
   86
  ],
  [
   "Japan",
   1988,
   81
  ],
  [
   "Sweden",
   1769,
   52
  ],
  [
   "Tunisia",
   1736,
   52
  ]
 ],
 "G": [
  [
   "Belgium",
   1949,
   93
  ],
  [
   "Iran",
   1886,
   80
  ],
  [
   "Egypt",
   1815,
   69
  ],
  [
   "New Zealand",
   1719,
   27
  ]
 ],
 "H": [
  [
   "Spain",
   2226,
   98
  ],
  [
   "Uruguay",
   1972,
   89
  ],
  [
   "Saudi Arabia",
   1683,
   34
  ],
  [
   "Cape Verde",
   1674,
   33
  ]
 ],
 "I": [
  [
   "France",
   2141,
   93
  ],
  [
   "Norway",
   1968,
   74
  ],
  [
   "Senegal",
   1921,
   77
  ],
  [
   "Iraq",
   1739,
   25
  ]
 ],
 "J": [
  [
   "Argentina",
   2186,
   98
  ],
  [
   "Austria",
   1887,
   73
  ],
  [
   "Algeria",
   1876,
   75
  ],
  [
   "Jordan",
   1779,
   22
  ]
 ],
 "K": [
  [
   "Colombia",
   2056,
   90
  ],
  [
   "Portugal",
   2038,
   92
  ],
  [
   "Uzbekistan",
   1822,
   42
  ],
  [
   "DR Congo",
   1773,
   38
  ]
 ],
 "L": [
  [
   "England",
   2082,
   97
  ],
  [
   "Croatia",
   1965,
   88
  ],
  [
   "Panama",
   1838,
   36
  ],
  [
   "Ghana",
   1610,
   41
  ]
 ]
}